rapclust/__init__.py
rapclust/eqnet.py
rapclust-0.1.1.data/scripts/RapClust
rapclust-0.1.1.dist-info/DESCRIPTION.rst
rapclust-0.1.1.dist-info/METADATA
rapclust-0.1.1.dist-info/RECORD
rapclust-0.1.1.dist-info/WHEEL
rapclust-0.1.1.dist-info/metadata.json
rapclust-0.1.1.dist-info/pbr.json
rapclust-0.1.1.dist-info/top_level.txt
