Metadata-Version: 2.0
Name: rapclust
Version: 0.1.1
Summary: Accurate, Fast and Lightweight Clustering of de novo Transcriptomes using Fragment Equivalence Classes
Home-page: https://github.com/COMBINE-lab/RapClust
Author: Avi Srivastava, Hirak Sarkar, Laraib Malik, Rob Patro
Author-email: rob.patro@cs.stonybrook.edu
License: BSD with attribution
Platform: UNKNOWN
Requires-Dist: PyYAML
Requires-Dist: click
Requires-Dist: networkx
Requires-Dist: numpy
Requires-Dist: pandas
